parzzley/.pylintrc
parzzley/__init__.py
parzzley/parzzley_cli.py
parzzley/asset/__init__.py
parzzley/asset/data.py
parzzley/asset/project_info.py
parzzley/asset/-static/README/en.pdf
parzzley/builtin/__init__.py
parzzley/builtin/aspects/__init__.py
parzzley/builtin/aspects/attach_sites.py
parzzley/builtin/aspects/conflicts.py
parzzley/builtin/aspects/default_sync.py
parzzley/builtin/aspects/directory.py
parzzley/builtin/aspects/exclude_paths.py
parzzley/builtin/aspects/item_type.py
parzzley/builtin/aspects/main_stream.py
parzzley/builtin/aspects/posix_attributes.py
parzzley/builtin/aspects/pull_and_purge.py
parzzley/builtin/aspects/remove.py
parzzley/builtin/aspects/revision_tracking.py
parzzley/builtin/aspects/streaming.py
parzzley/builtin/aspects/sync_report.py
parzzley/builtin/aspects/xattrs.py
parzzley/builtin/fs/__init__.py
parzzley/builtin/fs/local.py
parzzley/builtin/fs/ssh.py
parzzley/builtin/log_formatters/__init__.py
parzzley/builtin/log_formatters/html.py
parzzley/builtin/log_formatters/json.py
parzzley/builtin/log_outs/__init__.py
parzzley/builtin/log_outs/shell.py
parzzley/config/__init__.py
parzzley/config/loader.py
parzzley/config/file_formats/__init__.py
parzzley/config/file_formats/xml.py
parzzley/fs/__init__.py
parzzley/fs/stream.py
parzzley/fs/utils.py
parzzley/service/__init__.py
parzzley/sync/__init__.py
parzzley/sync/control.py
parzzley/sync/manager.py
parzzley/sync/run.py
parzzley/sync/utils.py
parzzley/sync/aspect/__init__.py
parzzley/sync/aspect/only_if.py
parzzley/sync/aspect/events/__init__.py
parzzley/sync/aspect/events/item/__init__.py
parzzley/sync/aspect/events/item/dir.py
parzzley/sync/aspect/events/item/stream.py
parzzley/sync/aspect/events/sync_run/__init__.py
parzzley/sync/engine/__init__.py
parzzley/sync/engine/event_runner.py
parzzley/sync/engine/events_impl.py
parzzley/sync/logger/__init__.py
parzzley/sync/logger/conditions.py
parzzley-4.0.3003.dist-info/METADATA
parzzley-4.0.3003.dist-info/WHEEL
parzzley-4.0.3003.dist-info/entry_points.txt
parzzley-4.0.3003.dist-info/top_level.txt
parzzley-4.0.3003.dist-info/RECORD
