Metadata-Version: 2.4
Name: parzzley
Version: 4.0.3003
Summary: a modular Python-based file synchronization tool
Home-page: https://pseudopolis.eu/pino/parzzley
Author: Josef Hahn
Author-email: parzzley@pseudopolis.eu
License: AGPL 3
Keywords: python filesystem file synchronization scripting
Requires-Dist: lxml~=6.0
Requires-Dist: watchdog~=6.0.0
Dynamic: author
Dynamic: author-email
Dynamic: description
Dynamic: description-content-type
Dynamic: home-page
Dynamic: keywords
Dynamic: license
Dynamic: requires-dist
Dynamic: summary
